thousandeyes_sdk/alerts/__init__.py
thousandeyes_sdk/alerts/py.typed
thousandeyes_sdk/alerts/api/__init__.py
thousandeyes_sdk/alerts/api/alert_rules_api.py
thousandeyes_sdk/alerts/api/alert_suppression_windows_api.py
thousandeyes_sdk/alerts/api/alerts_api.py
thousandeyes_sdk/alerts/models/__init__.py
thousandeyes_sdk/alerts/models/alert.py
thousandeyes_sdk/alerts/models/alert_detail.py
thousandeyes_sdk/alerts/models/alert_direction.py
thousandeyes_sdk/alerts/models/alert_embedded.py
thousandeyes_sdk/alerts/models/alert_group_type.py
thousandeyes_sdk/alerts/models/alert_links.py
thousandeyes_sdk/alerts/models/alert_meta.py
thousandeyes_sdk/alerts/models/alert_metric_detail.py
thousandeyes_sdk/alerts/models/alert_notification.py
thousandeyes_sdk/alerts/models/alert_rounds_violation_mode.py
thousandeyes_sdk/alerts/models/alert_simple_test.py
thousandeyes_sdk/alerts/models/alert_suppression_window.py
thousandeyes_sdk/alerts/models/alert_suppression_window_detail.py
thousandeyes_sdk/alerts/models/alert_suppression_window_request.py
thousandeyes_sdk/alerts/models/alert_suppression_window_state.py
thousandeyes_sdk/alerts/models/alert_suppression_windows.py
thousandeyes_sdk/alerts/models/alert_test_type.py
thousandeyes_sdk/alerts/models/alert_type.py
thousandeyes_sdk/alerts/models/alerts.py
thousandeyes_sdk/alerts/models/asn.py
thousandeyes_sdk/alerts/models/base_alert.py
thousandeyes_sdk/alerts/models/base_alert_suppression_window.py
thousandeyes_sdk/alerts/models/base_rule.py
thousandeyes_sdk/alerts/models/custom_webhook_integration_type.py
thousandeyes_sdk/alerts/models/days_of_week.py
thousandeyes_sdk/alerts/models/end_alert_metrics.py
thousandeyes_sdk/alerts/models/end_repeat.py
thousandeyes_sdk/alerts/models/end_repeat_type.py
thousandeyes_sdk/alerts/models/error.py
thousandeyes_sdk/alerts/models/expand_alert_test_options.py
thousandeyes_sdk/alerts/models/interval_type.py
thousandeyes_sdk/alerts/models/legacy_alert.py
thousandeyes_sdk_alerts-2.23.0.dist-info/licenses/LICENSE
thousandeyes_sdk_alerts-2.23.0.dist-info/licenses/NOTICE
thousandeyes_sdk_alerts-2.23.0.dist-info/METADATA
thousandeyes_sdk_alerts-2.23.0.dist-info/WHEEL
thousandeyes_sdk_alerts-2.23.0.dist-info/top_level.txt
thousandeyes_sdk_alerts-2.23.0.dist-info/RECORD
